{
  "db_name": "PostgreSQL",
  "query": "\n        INSERT INTO user_preferences (\n            user_id,\n            auto_subscribe,\n            email_notifications,\n            push_notifications,\n            theme,\n            language\n        )\n        VALUES (\n            $1, \n            COALESCE($2, true),\n            COALESCE($3, true), \n            COALESCE($4, true),\n            COALESCE($5, 'system'),\n            COALESCE($6, 'en')\n        )\n        ON CONFLICT (user_id)\n        DO UPDATE SET\n            auto_subscribe = COALESCE(EXCLUDED.auto_subscribe, user_preferences.auto_subscribe),\n            email_notifications = COALESCE(EXCLUDED.email_notifications, user_preferences.email_notifications),\n            push_notifications = COALESCE(EXCLUDED.push_notifications, user_preferences.push_notifications),\n            theme = COALESCE(EXCLUDED.theme, user_preferences.theme),\n            language = COALESCE(EXCLUDED.language, user_preferences.language)\n        ",
  "describe": {
    "columns": [],
    "parameters": {
      "Left": [
        "Varchar",
        "Bool",
        "Bool",
        "Bool",
        "Text",
        "Text"
      ]
    },
    "nullable": []
  },
  "hash": "6d145667c2701dbb849a144437d441bdb099d1e7b5bc2062ce741f11688f3143"
}
